MANIFEST.in
Makefile
README
Watershed-2.2.1.html
setup.py
Examples/LoG.py
Examples/README
Examples/artpic3.jpg
Examples/artpic4.jpg
Examples/automatic_output_segmentation_for_orchid.jpg
Examples/broken_rectangle1.jpg
Examples/cleanup.py
Examples/composite_image_with_all_marks_orchid.jpg
Examples/data_gen.py
Examples/dilate_erode.py
Examples/distance_mapping.py
Examples/distance_mapping2.py
Examples/edge_repair.py
Examples/extract_image_portion_and_apply_color_filter_demo.py
Examples/fruitlets2.jpg
Examples/hist_equalize_demo.py
Examples/influence_zones.py
Examples/marker_assisted_segmentation_for_orchid.jpg
Examples/orchid0001.jpg
Examples/otsu_threshold_hue_demo.py
Examples/segment_automatic_and_show_watershed.py
Examples/segment_automatic_and_use_contours_to_extract_blobs.py
Examples/segment_automatic_and_use_region_growing_to_extract_blobs.py
Examples/segment_with_markers_and_show_watershed.py
Examples/segment_with_markers_and_use_contours_to_extract_blobs.py
Examples/segment_with_markers_and_use_region_growing_to_extract_blobs.py
Examples/triangle1.jpg
Examples/triangle2.jpg
ExamplesImageScanner/AnalyzeScannerDump.py
ExamplesImageScanner/AnalyzeScannerDumpShowIntermediateResults.py
ExamplesImageScanner/AnalyzeSingleSubimage.py
ExamplesImageScanner/AnalyzeSingleSubimageShowIntermediateResults.py
ExamplesImageScanner/DSC00780.JPG
ExamplesImageScanner/DSC00781.JPG
ExamplesImageScanner/README
ExamplesImageScanner/RunImageScanner.py
ExamplesImageScanner/RunImageScannerInteractive.py
ImageScanner/ImageScanner.py
ImageScanner/__init__.py
TestWatershed/Test.py
TestWatershed/TestBinaryDilation.py
TestWatershed/TestImageLoadingAndDataExtraction.py
TestWatershed/Watershed.py
TestWatershed/line.jpg
Watershed/Watershed.py
Watershed/__init__.py
Watershed.egg-info/PKG-INFO
Watershed.egg-info/SOURCES.txt
Watershed.egg-info/dependency_links.txt
Watershed.egg-info/top_level.txt