Metadata-Version: 1.1
Name: Watershed
Version: 2.2.1
Summary: An image segmentation algorithm based on the watershed paradigm
Home-page: https://engineering.purdue.edu/kak/distWatershed/Watershed-2.2.1.html
Author: Avinash Kak
Author-email: kak@purdue.edu
License: Python Software Foundation License
Download-URL: https://engineering.purdue.edu/kak/distWatershed/Watershed-2.2.1.tar.gz
Keywords: image processing,image segmentation,computer vision
Platform: All platforms
Classifier: Topic :: Scientific/Engineering :: Image Recognition
Classifier: Programming Language :: Python :: 2.7
Classifier: Programming Language :: Python :: 3.6
